{"nodes": [{"id": "f_finoqz_main_finoqz_main_frontend_app_admin_dash_dashboard_components_dashboard_categoryparticipation_tsx", "label": "CategoryParticipation.tsx", "file_type": "code", "source_file": "F:\\FinoQz-main\\FinoQz-main\\frontend\\app\\admin_dash\\dashboard\\components\\dashboard\\CategoryParticipation.tsx", "source_location": "L1"}, {"id": "categoryparticipation_fetchdata", "label": "fetchData()", "file_type": "code", "source_file": "F:\\FinoQz-main\\FinoQz-main\\frontend\\app\\admin_dash\\dashboard\\components\\dashboard\\CategoryParticipation.tsx", "source_location": "L18"}], "edges": [{"source": "f_finoqz_main_finoqz_main_frontend_app_admin_dash_dashboard_components_dashboard_categoryparticipation_tsx", "target": "react", "relation": "imports_from", "confidence": "EXTRACTED", "source_file": "F:\\FinoQz-main\\FinoQz-main\\frontend\\app\\admin_dash\\dashboard\\components\\dashboard\\CategoryParticipation.tsx", "source_location": "L1", "weight": 1.0}, {"source": "f_finoqz_main_finoqz_main_frontend_app_admin_dash_dashboard_components_dashboard_categoryparticipation_tsx", "target": "lucide_react", "relation": "imports_from", "confidence": "EXTRACTED", "source_file": "F:\\FinoQz-main\\FinoQz-main\\frontend\\app\\admin_dash\\dashboard\\components\\dashboard\\CategoryParticipation.tsx", "source_location": "L2", "weight": 1.0}, {"source": "f_finoqz_main_finoqz_main_frontend_app_admin_dash_dashboard_components_dashboard_categoryparticipation_tsx", "target": "categoryparticipation_fetchdata", "relation": "contains", "confidence": "EXTRACTED", "source_file": "F:\\FinoQz-main\\FinoQz-main\\frontend\\app\\admin_dash\\dashboard\\components\\dashboard\\CategoryParticipation.tsx", "source_location": "L18", "weight": 1.0}], "raw_calls": [{"caller_nid": "categoryparticipation_fetchdata", "callee": "get", "source_file": "F:\\FinoQz-main\\FinoQz-main\\frontend\\app\\admin_dash\\dashboard\\components\\dashboard\\CategoryParticipation.tsx", "source_location": "L20"}, {"caller_nid": "categoryparticipation_fetchdata", "callee": "import", "source_file": "F:\\FinoQz-main\\FinoQz-main\\frontend\\app\\admin_dash\\dashboard\\components\\dashboard\\CategoryParticipation.tsx", "source_location": "L20"}, {"caller_nid": "categoryparticipation_fetchdata", "callee": "setCategories", "source_file": "F:\\FinoQz-main\\FinoQz-main\\frontend\\app\\admin_dash\\dashboard\\components\\dashboard\\CategoryParticipation.tsx", "source_location": "L21"}, {"caller_nid": "categoryparticipation_fetchdata", "callee": "setCategories", "source_file": "F:\\FinoQz-main\\FinoQz-main\\frontend\\app\\admin_dash\\dashboard\\components\\dashboard\\CategoryParticipation.tsx", "source_location": "L23"}, {"caller_nid": "categoryparticipation_fetchdata", "callee": "setLoading", "source_file": "F:\\FinoQz-main\\FinoQz-main\\frontend\\app\\admin_dash\\dashboard\\components\\dashboard\\CategoryParticipation.tsx", "source_location": "L25"}]}