{"nodes": [{"id": "f_finoqz_main_finoqz_main_frontend_utils_exportutils_ts", "label": "exportUtils.ts", "file_type": "code", "source_file": "F:\\FinoQz-main\\FinoQz-main\\frontend\\utils\\exportUtils.ts", "source_location": "L1"}, {"id": "exportutils_exporttoexcel", "label": "exportToExcel()", "file_type": "code", "source_file": "F:\\FinoQz-main\\FinoQz-main\\frontend\\utils\\exportUtils.ts", "source_location": "L14"}, {"id": "exportutils_exporttojson", "label": "exportToJSON()", "file_type": "code", "source_file": "F:\\FinoQz-main\\FinoQz-main\\frontend\\utils\\exportUtils.ts", "source_location": "L34"}, {"id": "exportutils_exporttopdf", "label": "exportToPDF()", "file_type": "code", "source_file": "F:\\FinoQz-main\\FinoQz-main\\frontend\\utils\\exportUtils.ts", "source_location": "L41"}, {"id": "exportutils_exportsuggestionstoexcel", "label": "exportSuggestionsToExcel()", "file_type": "code", "source_file": "F:\\FinoQz-main\\FinoQz-main\\frontend\\utils\\exportUtils.ts", "source_location": "L55"}, {"id": "exportutils_exportsuggestionstopdf", "label": "exportSuggestionsToPDF()", "file_type": "code", "source_file": "F:\\FinoQz-main\\FinoQz-main\\frontend\\utils\\exportUtils.ts", "source_location": "L73"}, {"id": "exportutils_exportparticipantstoexcel", "label": "exportParticipantsToExcel()", "file_type": "code", "source_file": "F:\\FinoQz-main\\FinoQz-main\\frontend\\utils\\exportUtils.ts", "source_location": "L92"}, {"id": "exportutils_exportparticipantstopdf", "label": "exportParticipantsToPDF()", "file_type": "code", "source_file": "F:\\FinoQz-main\\FinoQz-main\\frontend\\utils\\exportUtils.ts", "source_location": "L117"}, {"id": "exportutils_exportleaderboardtoexcel", "label": "exportLeaderboardToExcel()", "file_type": "code", "source_file": "F:\\FinoQz-main\\FinoQz-main\\frontend\\utils\\exportUtils.ts", "source_location": "L139"}, {"id": "exportutils_exportleaderboardtopdf", "label": "exportLeaderboardToPDF()", "file_type": "code", "source_file": "F:\\FinoQz-main\\FinoQz-main\\frontend\\utils\\exportUtils.ts", "source_location": "L160"}], "edges": [{"source": "f_finoqz_main_finoqz_main_frontend_utils_exportutils_ts", "target": "exceljs", "relation": "imports_from", "confidence": "EXTRACTED", "source_file": "F:\\FinoQz-main\\FinoQz-main\\frontend\\utils\\exportUtils.ts", "source_location": "L1", "weight": 1.0}, {"source": "f_finoqz_main_finoqz_main_frontend_utils_exportutils_ts", "target": "jspdf", "relation": "imports_from", "confidence": "EXTRACTED", "source_file": "F:\\FinoQz-main\\FinoQz-main\\frontend\\utils\\exportUtils.ts", "source_location": "L2", "weight": 1.0}, {"source": "f_finoqz_main_finoqz_main_frontend_utils_exportutils_ts", "target": "jspdf_autotable", "relation": "imports_from", "confidence": "EXTRACTED", "source_file": "F:\\FinoQz-main\\FinoQz-main\\frontend\\utils\\exportUtils.ts", "source_location": "L3", "weight": 1.0}, {"source": "f_finoqz_main_finoqz_main_frontend_utils_exportutils_ts", "target": "exportutils_exporttoexcel", "relation": "contains", "confidence": "EXTRACTED", "source_file": "F:\\FinoQz-main\\FinoQz-main\\frontend\\utils\\exportUtils.ts", "source_location": "L14", "weight": 1.0}, {"source": "f_finoqz_main_finoqz_main_frontend_utils_exportutils_ts", "target": "exportutils_exporttojson", "relation": "contains", "confidence": "EXTRACTED", "source_file": "F:\\FinoQz-main\\FinoQz-main\\frontend\\utils\\exportUtils.ts", "source_location": "L34", "weight": 1.0}, {"source": "f_finoqz_main_finoqz_main_frontend_utils_exportutils_ts", "target": "exportutils_exporttopdf", "relation": "contains", "confidence": "EXTRACTED", "source_file": "F:\\FinoQz-main\\FinoQz-main\\frontend\\utils\\exportUtils.ts", "source_location": "L41", "weight": 1.0}, {"source": "f_finoqz_main_finoqz_main_frontend_utils_exportutils_ts", "target": "exportutils_exportsuggestionstoexcel", "relation": "contains", "confidence": "EXTRACTED", "source_file": "F:\\FinoQz-main\\FinoQz-main\\frontend\\utils\\exportUtils.ts", "source_location": "L55", "weight": 1.0}, {"source": "f_finoqz_main_finoqz_main_frontend_utils_exportutils_ts", "target": "exportutils_exportsuggestionstopdf", "relation": "contains", "confidence": "EXTRACTED", "source_file": "F:\\FinoQz-main\\FinoQz-main\\frontend\\utils\\exportUtils.ts", "source_location": "L73", "weight": 1.0}, {"source": "f_finoqz_main_finoqz_main_frontend_utils_exportutils_ts", "target": "exportutils_exportparticipantstoexcel", "relation": "contains", "confidence": "EXTRACTED", "source_file": "F:\\FinoQz-main\\FinoQz-main\\frontend\\utils\\exportUtils.ts", "source_location": "L92", "weight": 1.0}, {"source": "f_finoqz_main_finoqz_main_frontend_utils_exportutils_ts", "target": "exportutils_exportparticipantstopdf", "relation": "contains", "confidence": "EXTRACTED", "source_file": "F:\\FinoQz-main\\FinoQz-main\\frontend\\utils\\exportUtils.ts", "source_location": "L117", "weight": 1.0}, {"source": "f_finoqz_main_finoqz_main_frontend_utils_exportutils_ts", "target": "exportutils_exportleaderboardtoexcel", "relation": "contains", "confidence": "EXTRACTED", "source_file": "F:\\FinoQz-main\\FinoQz-main\\frontend\\utils\\exportUtils.ts", "source_location": "L139", "weight": 1.0}, {"source": "f_finoqz_main_finoqz_main_frontend_utils_exportutils_ts", "target": "exportutils_exportleaderboardtopdf", "relation": "contains", "confidence": "EXTRACTED", "source_file": "F:\\FinoQz-main\\FinoQz-main\\frontend\\utils\\exportUtils.ts", "source_location": "L160", "weight": 1.0}], "raw_calls": [{"caller_nid": "exportutils_exporttoexcel", "callee": "addWorksheet", "source_file": "F:\\FinoQz-main\\FinoQz-main\\frontend\\utils\\exportUtils.ts", "source_location": "L16"}, {"caller_nid": "exportutils_exporttoexcel", "callee": "forEach", "source_file": "F:\\FinoQz-main\\FinoQz-main\\frontend\\utils\\exportUtils.ts", "source_location": "L25"}, {"caller_nid": "exportutils_exporttoexcel", "callee": "writeBuffer", "source_file": "F:\\FinoQz-main\\FinoQz-main\\frontend\\utils\\exportUtils.ts", "source_location": "L26"}, {"caller_nid": "exportutils_exporttoexcel", "callee": "createObjectURL", "source_file": "F:\\FinoQz-main\\FinoQz-main\\frontend\\utils\\exportUtils.ts", "source_location": "L28"}, {"caller_nid": "exportutils_exporttoexcel", "callee": "createElement", "source_file": "F:\\FinoQz-main\\FinoQz-main\\frontend\\utils\\exportUtils.ts", "source_location": "L29"}, {"caller_nid": "exportutils_exporttoexcel", "callee": "click", "source_file": "F:\\FinoQz-main\\FinoQz-main\\frontend\\utils\\exportUtils.ts", "source_location": "L30"}, {"caller_nid": "exportutils_exporttoexcel", "callee": "revokeObjectURL", "source_file": "F:\\FinoQz-main\\FinoQz-main\\frontend\\utils\\exportUtils.ts", "source_location": "L31"}, {"caller_nid": "exportutils_exporttojson", "callee": "stringify", "source_file": "F:\\FinoQz-main\\FinoQz-main\\frontend\\utils\\exportUtils.ts", "source_location": "L35"}, {"caller_nid": "exportutils_exporttojson", "callee": "createObjectURL", "source_file": "F:\\FinoQz-main\\FinoQz-main\\frontend\\utils\\exportUtils.ts", "source_location": "L36"}, {"caller_nid": "exportutils_exporttojson", "callee": "createElement", "source_file": "F:\\FinoQz-main\\FinoQz-main\\frontend\\utils\\exportUtils.ts", "source_location": "L37"}, {"caller_nid": "exportutils_exporttojson", "callee": "click", "source_file": "F:\\FinoQz-main\\FinoQz-main\\frontend\\utils\\exportUtils.ts", "source_location": "L38"}, {"caller_nid": "exportutils_exporttopdf", "callee": "map", "source_file": "F:\\FinoQz-main\\FinoQz-main\\frontend\\utils\\exportUtils.ts", "source_location": "L45"}, {"caller_nid": "exportutils_exporttopdf", "callee": "autoTable", "source_file": "F:\\FinoQz-main\\FinoQz-main\\frontend\\utils\\exportUtils.ts", "source_location": "L46"}, {"caller_nid": "exportutils_exporttopdf", "callee": "save", "source_file": "F:\\FinoQz-main\\FinoQz-main\\frontend\\utils\\exportUtils.ts", "source_location": "L47"}, {"caller_nid": "exportutils_exportsuggestionstoexcel", "callee": "addWorksheet", "source_file": "F:\\FinoQz-main\\FinoQz-main\\frontend\\utils\\exportUtils.ts", "source_location": "L57"}, {"caller_nid": "exportutils_exportsuggestionstoexcel", "callee": "forEach", "source_file": "F:\\FinoQz-main\\FinoQz-main\\frontend\\utils\\exportUtils.ts", "source_location": "L64"}, {"caller_nid": "exportutils_exportsuggestionstoexcel", "callee": "writeBuffer", "source_file": "F:\\FinoQz-main\\FinoQz-main\\frontend\\utils\\exportUtils.ts", "source_location": "L65"}, {"caller_nid": "exportutils_exportsuggestionstoexcel", "callee": "createObjectURL", "source_file": "F:\\FinoQz-main\\FinoQz-main\\frontend\\utils\\exportUtils.ts", "source_location": "L67"}, {"caller_nid": "exportutils_exportsuggestionstoexcel", "callee": "createElement", "source_file": "F:\\FinoQz-main\\FinoQz-main\\frontend\\utils\\exportUtils.ts", "source_location": "L68"}, {"caller_nid": "exportutils_exportsuggestionstoexcel", "callee": "click", "source_file": "F:\\FinoQz-main\\FinoQz-main\\frontend\\utils\\exportUtils.ts", "source_location": "L69"}, {"caller_nid": "exportutils_exportsuggestionstoexcel", "callee": "revokeObjectURL", "source_file": "F:\\FinoQz-main\\FinoQz-main\\frontend\\utils\\exportUtils.ts", "source_location": "L70"}, {"caller_nid": "exportutils_exportsuggestionstopdf", "callee": "map", "source_file": "F:\\FinoQz-main\\FinoQz-main\\frontend\\utils\\exportUtils.ts", "source_location": "L77"}, {"caller_nid": "exportutils_exportsuggestionstopdf", "callee": "autoTable", "source_file": "F:\\FinoQz-main\\FinoQz-main\\frontend\\utils\\exportUtils.ts", "source_location": "L78"}, {"caller_nid": "exportutils_exportsuggestionstopdf", "callee": "save", "source_file": "F:\\FinoQz-main\\FinoQz-main\\frontend\\utils\\exportUtils.ts", "source_location": "L79"}, {"caller_nid": "exportutils_exportparticipantstoexcel", "callee": "addWorksheet", "source_file": "F:\\FinoQz-main\\FinoQz-main\\frontend\\utils\\exportUtils.ts", "source_location": "L94"}, {"caller_nid": "exportutils_exportparticipantstoexcel", "callee": "getRow", "source_file": "F:\\FinoQz-main\\FinoQz-main\\frontend\\utils\\exportUtils.ts", "source_location": "L105"}, {"caller_nid": "exportutils_exportparticipantstoexcel", "callee": "forEach", "source_file": "F:\\FinoQz-main\\FinoQz-main\\frontend\\utils\\exportUtils.ts", "source_location": "L108"}, {"caller_nid": "exportutils_exportparticipantstoexcel", "callee": "writeBuffer", "source_file": "F:\\FinoQz-main\\FinoQz-main\\frontend\\utils\\exportUtils.ts", "source_location": "L109"}, {"caller_nid": "exportutils_exportparticipantstoexcel", "callee": "createObjectURL", "source_file": "F:\\FinoQz-main\\FinoQz-main\\frontend\\utils\\exportUtils.ts", "source_location": "L111"}, {"caller_nid": "exportutils_exportparticipantstoexcel", "callee": "createElement", "source_file": "F:\\FinoQz-main\\FinoQz-main\\frontend\\utils\\exportUtils.ts", "source_location": "L112"}, {"caller_nid": "exportutils_exportparticipantstoexcel", "callee": "replace", "source_file": "F:\\FinoQz-main\\FinoQz-main\\frontend\\utils\\exportUtils.ts", "source_location": "L113"}, {"caller_nid": "exportutils_exportparticipantstoexcel", "callee": "click", "source_file": "F:\\FinoQz-main\\FinoQz-main\\frontend\\utils\\exportUtils.ts", "source_location": "L113"}, {"caller_nid": "exportutils_exportparticipantstoexcel", "callee": "revokeObjectURL", "source_file": "F:\\FinoQz-main\\FinoQz-main\\frontend\\utils\\exportUtils.ts", "source_location": "L114"}, {"caller_nid": "exportutils_exportparticipantstopdf", "callee": "setFontSize", "source_file": "F:\\FinoQz-main\\FinoQz-main\\frontend\\utils\\exportUtils.ts", "source_location": "L119"}, {"caller_nid": "exportutils_exportparticipantstopdf", "callee": "text", "source_file": "F:\\FinoQz-main\\FinoQz-main\\frontend\\utils\\exportUtils.ts", "source_location": "L119"}, {"caller_nid": "exportutils_exportparticipantstopdf", "callee": "setFontSize", "source_file": "F:\\FinoQz-main\\FinoQz-main\\frontend\\utils\\exportUtils.ts", "source_location": "L120"}, {"caller_nid": "exportutils_exportparticipantstopdf", "callee": "text", "source_file": "F:\\FinoQz-main\\FinoQz-main\\frontend\\utils\\exportUtils.ts", "source_location": "L120"}, {"caller_nid": "exportutils_exportparticipantstopdf", "callee": "toLocaleString", "source_file": "F:\\FinoQz-main\\FinoQz-main\\frontend\\utils\\exportUtils.ts", "source_location": "L120"}, {"caller_nid": "exportutils_exportparticipantstopdf", "callee": "autoTable", "source_file": "F:\\FinoQz-main\\FinoQz-main\\frontend\\utils\\exportUtils.ts", "source_location": "L121"}, {"caller_nid": "exportutils_exportparticipantstopdf", "callee": "map", "source_file": "F:\\FinoQz-main\\FinoQz-main\\frontend\\utils\\exportUtils.ts", "source_location": "L124"}, {"caller_nid": "exportutils_exportparticipantstopdf", "callee": "save", "source_file": "F:\\FinoQz-main\\FinoQz-main\\frontend\\utils\\exportUtils.ts", "source_location": "L128"}, {"caller_nid": "exportutils_exportparticipantstopdf", "callee": "replace", "source_file": "F:\\FinoQz-main\\FinoQz-main\\frontend\\utils\\exportUtils.ts", "source_location": "L128"}, {"caller_nid": "exportutils_exportleaderboardtoexcel", "callee": "addWorksheet", "source_file": "F:\\FinoQz-main\\FinoQz-main\\frontend\\utils\\exportUtils.ts", "source_location": "L141"}, {"caller_nid": "exportutils_exportleaderboardtoexcel", "callee": "getRow", "source_file": "F:\\FinoQz-main\\FinoQz-main\\frontend\\utils\\exportUtils.ts", "source_location": "L148"}, {"caller_nid": "exportutils_exportleaderboardtoexcel", "callee": "forEach", "source_file": "F:\\FinoQz-main\\FinoQz-main\\frontend\\utils\\exportUtils.ts", "source_location": "L151"}, {"caller_nid": "exportutils_exportleaderboardtoexcel", "callee": "writeBuffer", "source_file": "F:\\FinoQz-main\\FinoQz-main\\frontend\\utils\\exportUtils.ts", "source_location": "L152"}, {"caller_nid": "exportutils_exportleaderboardtoexcel", "callee": "createObjectURL", "source_file": "F:\\FinoQz-main\\FinoQz-main\\frontend\\utils\\exportUtils.ts", "source_location": "L154"}, {"caller_nid": "exportutils_exportleaderboardtoexcel", "callee": "createElement", "source_file": "F:\\FinoQz-main\\FinoQz-main\\frontend\\utils\\exportUtils.ts", "source_location": "L155"}, {"caller_nid": "exportutils_exportleaderboardtoexcel", "callee": "replace", "source_file": "F:\\FinoQz-main\\FinoQz-main\\frontend\\utils\\exportUtils.ts", "source_location": "L156"}, {"caller_nid": "exportutils_exportleaderboardtoexcel", "callee": "click", "source_file": "F:\\FinoQz-main\\FinoQz-main\\frontend\\utils\\exportUtils.ts", "source_location": "L156"}, {"caller_nid": "exportutils_exportleaderboardtoexcel", "callee": "revokeObjectURL", "source_file": "F:\\FinoQz-main\\FinoQz-main\\frontend\\utils\\exportUtils.ts", "source_location": "L157"}, {"caller_nid": "exportutils_exportleaderboardtopdf", "callee": "setFontSize", "source_file": "F:\\FinoQz-main\\FinoQz-main\\frontend\\utils\\exportUtils.ts", "source_location": "L162"}, {"caller_nid": "exportutils_exportleaderboardtopdf", "callee": "text", "source_file": "F:\\FinoQz-main\\FinoQz-main\\frontend\\utils\\exportUtils.ts", "source_location": "L162"}, {"caller_nid": "exportutils_exportleaderboardtopdf", "callee": "setFontSize", "source_file": "F:\\FinoQz-main\\FinoQz-main\\frontend\\utils\\exportUtils.ts", "source_location": "L163"}, {"caller_nid": "exportutils_exportleaderboardtopdf", "callee": "text", "source_file": "F:\\FinoQz-main\\FinoQz-main\\frontend\\utils\\exportUtils.ts", "source_location": "L163"}, {"caller_nid": "exportutils_exportleaderboardtopdf", "callee": "toLocaleString", "source_file": "F:\\FinoQz-main\\FinoQz-main\\frontend\\utils\\exportUtils.ts", "source_location": "L163"}, {"caller_nid": "exportutils_exportleaderboardtopdf", "callee": "autoTable", "source_file": "F:\\FinoQz-main\\FinoQz-main\\frontend\\utils\\exportUtils.ts", "source_location": "L164"}, {"caller_nid": "exportutils_exportleaderboardtopdf", "callee": "map", "source_file": "F:\\FinoQz-main\\FinoQz-main\\frontend\\utils\\exportUtils.ts", "source_location": "L167"}, {"caller_nid": "exportutils_exportleaderboardtopdf", "callee": "save", "source_file": "F:\\FinoQz-main\\FinoQz-main\\frontend\\utils\\exportUtils.ts", "source_location": "L171"}, {"caller_nid": "exportutils_exportleaderboardtopdf", "callee": "replace", "source_file": "F:\\FinoQz-main\\FinoQz-main\\frontend\\utils\\exportUtils.ts", "source_location": "L171"}]}